autosweep/__init__.py
autosweep/test_exec.py
autosweep/data_types/__init__.py
autosweep/data_types/filereader.py
autosweep/data_types/metadata.py
autosweep/data_types/recipe.py
autosweep/data_types/station_config.py
autosweep/exec_helpers/__init__.py
autosweep/exec_helpers/reporter.py
autosweep/exec_helpers/status_writer.py
autosweep/exec_helpers/html/template.html
autosweep/instruments/__init__.py
autosweep/instruments/abs_instr.py
autosweep/instruments/instrument_manager.py
autosweep/instruments/virt_instr.py
autosweep/instruments/coms/__init__.py
autosweep/instruments/coms/base_com.py
autosweep/instruments/coms/visa_coms.py
autosweep/instruments/optical/DiConGP600.py
autosweep/instruments/optical/Keysight8164B.py
autosweep/instruments/optical/KeysightN7745C.py
autosweep/instruments/optical/KeysightN777C.py
autosweep/instruments/optical/KeysightN778C.py
autosweep/sweep/__init__.py
autosweep/sweep/io.py
autosweep/sweep/sweep_parser.py
autosweep/sweep/vis_utils.py
autosweep/tests/__init__.py
autosweep/tests/abs_test.py
autosweep/tests/virt_test.py
autosweep/tests/wvl_sweep.py
autosweep/utils/__init__.py
autosweep/utils/generics.py
autosweep/utils/io.py
autosweep/utils/logger.py
autosweep/utils/params.py
autosweep/utils/registrar.py
autosweep/utils/ta_math.py
autosweep/utils/typing_ext.py
autosweep-0.1.0.dist-info/LICENSE
autosweep-0.1.0.dist-info/WHEEL
autosweep-0.1.0.dist-info/METADATA
autosweep-0.1.0.dist-info/RECORD
