Metadata-Version: 2.1
Name: autosweep
Version: 0.1.0
Summary: automated testing
Keywords: python
Author-email: gdsfactory <contact@gdsfactory.com>
Requires-Python: >=3.10
Classifier: Programming Language :: Python :: 3.10
Classifier: Programming Language :: Python :: 3.11
Classifier: Operating System :: OS Independent
Requires-Dist: matplotlib
Requires-Dist: numpy
Requires-Dist: orjson
Requires-Dist: jinja2
Requires-Dist: pyvisa
Requires-Dist: pre-commit ; extra == "dev"
Requires-Dist: pytest ; extra == "dev"
Requires-Dist: pytest-cov ; extra == "dev"
Requires-Dist: pytest_regressions ; extra == "dev"
Requires-Dist: pyvisa-py ; extra == "dev"
Requires-Dist: towncrier ; extra == "dev"
Requires-Dist: tbump ; extra == "dev"
Requires-Dist: jupytext ; extra == "docs"
Requires-Dist: pydata_sphinx_theme==0.14.0 ; extra == "docs"
Requires-Dist: matplotlib ; extra == "docs"
Requires-Dist: jupyter-book==0.15.1 ; extra == "docs"
Provides-Extra: dev
Provides-Extra: docs
